app/__init__.py
app/cli.py
codebuddy_ai-0.2.2.dist-info/LICENSE.txt
codebuddy_ai-0.2.2.dist-info/METADATA
codebuddy_ai-0.2.2.dist-info/WHEEL
codebuddy_ai-0.2.2.dist-info/entry_points.txt
codebuddy_ai-0.2.2.dist-info/top_level.txt
codebuddy_ai-0.2.2.dist-info/RECORD
