Metadata-Version: 2.2
Name: codebuddy-ai
Version: 0.2.2
Summary: AI-powered CLI to generate commit messages, review code, and suggest fixes
Home-page: https://github.com/UP11SRE/agent-client
Author: Naman Kansal
Author-email: namankansal91@gmail.com
License: Proprietary
Classifier: Development Status :: 4 - Beta
Classifier: Programming Language :: Python :: 3
Classifier: Operating System :: OS Independent
Requires-Python: >=3.6
License-File: LICENSE.txt
Requires-Dist: requests
Dynamic: author
Dynamic: author-email
Dynamic: classifier
Dynamic: description
Dynamic: description-content-type
Dynamic: home-page
Dynamic: license
Dynamic: requires-dist
Dynamic: requires-python
Dynamic: summary
